open_dive/__init__.py
open_dive/viz.py
open_dive/scripts/run.py
open_dive-0.3.0.dist-info/licenses/LICENSE
open_dive-0.3.0.dist-info/METADATA
open_dive-0.3.0.dist-info/WHEEL
open_dive-0.3.0.dist-info/entry_points.txt
open_dive-0.3.0.dist-info/top_level.txt
open_dive-0.3.0.dist-info/RECORD
