Metadata-Version: 2.4
Name: open-dive
Version: 0.3.0
Summary: OpenDIVE (Open Diffusion Imaging Visualization for Everyone) is a command line interface tool for generating accessible, interpretable visualizations from diffusion MRI.
Maintainer-email: Adam Saunders <adam.m.saunders@vanderbilt.edu>, Elyssa McMaster <elyssa.m.mcmaster@vanderbilt.edu>
Project-URL: Repository, https://github.com/MASILab/open_dive
Project-URL: Issues, https://github.com/MASILab/open_dive/issues
Keywords: diffusion MRI,visualization,medical imaging
Requires-Python: >=3.10
License-File: LICENSE
Requires-Dist: cmcrameri>=1.9
Requires-Dist: dipy>=1.10.0
Requires-Dist: fury>=0.12.0
Requires-Dist: scikit-image>=0.25.1
Dynamic: license-file
